README.md
pwhois
setup.cfg
setup.py
whois_alt/__init__.py
whois_alt/airports.dat
whois_alt/countries.dat
whois_alt/countries3.dat
whois_alt/net.py
whois_alt/parse.py
whois_alt/shared.py
whois_alt/states_au.dat
whois_alt/states_ca.dat
whois_alt/states_us.dat
whois_alt.egg-info/PKG-INFO
whois_alt.egg-info/SOURCES.txt
whois_alt.egg-info/dependency_links.txt
whois_alt.egg-info/requires.txt
whois_alt.egg-info/top_level.txt