Metadata-Version: 2.1
Name: whois-alt
Version: 2.4.5
Summary: Module for retrieving and parsing the WHOIS data for a domain. Supports most domains. No dependencies. Fork of pythonwhois-alt as we need quick bug fixes
Home-page: https://gitlab.com/keychest/whois-alt-for-python
Author: KeyChest
Author-email: support@keychest.net
License: MIT
Keywords: whois nic domain
Platform: UNKNOWN
Classifier: Environment :: Web Environment
Classifier: Intended Audience :: Developers
Classifier: Operating System :: OS Independent
Classifier: Programming Language :: Python
Classifier: Programming Language :: Python :: 3
Classifier: Programming Language :: Python :: 3.6
Classifier: Programming Language :: Python :: 3.7
Classifier: Programming Language :: Python :: 3.8
Classifier: Topic :: Internet :: Name Service (DNS)
Provides: whois_alt
